yt2doc/__init__.py
yt2doc/__main__.py
yt2doc/cli.py
yt2doc/factories.py
yt2doc/timer.py
yt2doc/writer.py
yt2doc/yt2doc.py
yt2doc/extraction/__init__.py
yt2doc/extraction/extractor.py
yt2doc/extraction/file_cache.py
yt2doc/extraction/interfaces.py
yt2doc/formatting/__init__.py
yt2doc/formatting/formatter.py
yt2doc/formatting/interfaces.py
yt2doc/formatting/llm_topic_segmenter.py
yt2doc/transcription/__init__.py
yt2doc/transcription/faster_whisper_adapter.py
yt2doc/transcription/interfaces.py
yt2doc/transcription/transcriber.py
yt2doc/transcription/whisper_cpp_adapter.py
yt2doc/youtube/__init__.py
yt2doc/youtube/interfaces.py
yt2doc/youtube/yt_video_info_extractor.py
yt_extractor-0.1.0.dist-info/LICENSE
yt_extractor-0.1.0.dist-info/METADATA
yt_extractor-0.1.0.dist-info/WHEEL
yt_extractor-0.1.0.dist-info/entry_points.txt
yt_extractor-0.1.0.dist-info/top_level.txt
yt_extractor-0.1.0.dist-info/RECORD
